{
  "input": "./Flows from The Unwavering Ground/Flows from The Unwavering Ground/Prelude and Fugue for Recorders in G - Full score - 01 Fugue.musicxml",
  "violations": [
    {
      "rule": "Leading tone unresolved",
      "measure": 3,
      "beat": 4,
      "timeDiv": 44,
      "partIndices": [
        1
      ],
      "voiceNames": "Alto Recorder",
      "detail": "LT F# → E (expected tonic G)"
    },
    {
      "rule": "Parallel P5ths",
      "measure": 4,
      "beat": 2,
      "timeDiv": 52,
      "partIndices": [
        0,
        1
      ],
      "voiceNames": "Soprano Recorder & Alto Recorder",
      "detail": "P5 → P5 (B-E → A-D)",
      "noteTargets": [
        {
          "partIndex": 0,
          "startDiv": 50
        },
        {
          "partIndex": 1,
          "startDiv": 48
        },
        {
          "partIndex": 0,
          "startDiv": 52
        },
        {
          "partIndex": 1,
          "startDiv": 52
        }
      ]
    },
    {
      "rule": "Leading tone unresolved",
      "measure": 6,
      "beat": 1.5,
      "timeDiv": 82,
      "partIndices": [
        1
      ],
      "voiceNames": "Alto Recorder",
      "detail": "LT F# → E (expected tonic G)"
    },
    {
      "rule": "Parallel octaves",
      "measure": 6,
      "beat": 2,
      "timeDiv": 84,
      "partIndices": [
        0,
        2
      ],
      "voiceNames": "Soprano Recorder & Tenor Recorder",
      "detail": "P8 → P8 (A-A → G-G)",
      "noteTargets": [
        {
          "partIndex": 0,
          "startDiv": 82
        },
        {
          "partIndex": 2,
          "startDiv": 80
        },
        {
          "partIndex": 0,
          "startDiv": 84
        },
        {
          "partIndex": 2,
          "startDiv": 84
        }
      ]
    },
    {
      "rule": "Leading tone unresolved",
      "measure": 7,
      "beat": 1,
      "timeDiv": 96,
      "partIndices": [
        1
      ],
      "voiceNames": "Alto Recorder",
      "detail": "LT F# → E (expected tonic G)"
    },
    {
      "rule": "Leading tone unresolved",
      "measure": 7,
      "beat": 2,
      "timeDiv": 100,
      "partIndices": [
        0
      ],
      "voiceNames": "Soprano Recorder",
      "detail": "LT F# → A (expected tonic G)"
    },
    {
      "rule": "Parallel octaves",
      "measure": 7,
      "beat": 3,
      "timeDiv": 104,
      "partIndices": [
        0,
        3
      ],
      "voiceNames": "Soprano Recorder & Bass Recorder",
      "detail": "P8 → P8 (A-A → G-G)",
      "noteTargets": [
        {
          "partIndex": 0,
          "startDiv": 102
        },
        {
          "partIndex": 3,
          "startDiv": 100
        },
        {
          "partIndex": 0,
          "startDiv": 104
        },
        {
          "partIndex": 3,
          "startDiv": 104
        }
      ]
    },
    {
      "rule": "Leading tone unresolved",
      "measure": 8,
      "beat": 2.5,
      "timeDiv": 118,
      "partIndices": [
        1
      ],
      "voiceNames": "Alto Recorder",
      "detail": "LT F# → E (expected tonic G)"
    },
    {
      "rule": "Voice crossing",
      "measure": 9,
      "beat": 1,
      "timeDiv": 128,
      "partIndices": [
        1,
        2
      ],
      "voiceNames": "Alto Recorder & Tenor Recorder",
      "detail": "Alto Recorder crosses Tenor Recorder (G vs C)"
    },
    {
      "rule": "Large leap",
      "measure": 9,
      "beat": 1,
      "timeDiv": 128,
      "partIndices": [
        1
      ],
      "voiceNames": "Alto Recorder",
      "detail": "leap of 11 semitones: F# → G"
    },
    {
      "rule": "Voice crossing",
      "measure": 9,
      "beat": 2,
      "timeDiv": 132,
      "partIndices": [
        1,
        2
      ],
      "voiceNames": "Alto Recorder & Tenor Recorder",
      "detail": "Alto Recorder crosses Tenor Recorder (D vs A)"
    },
    {
      "rule": "Voice crossing",
      "measure": 9,
      "beat": 4,
      "timeDiv": 140,
      "partIndices": [
        1,
        3
      ],
      "voiceNames": "Alto Recorder & Bass Recorder",
      "detail": "Alto Recorder crosses Bass Recorder (B vs C)"
    },
    {
      "rule": "Leading tone unresolved",
      "measure": 10,
      "beat": 1,
      "timeDiv": 144,
      "partIndices": [
        2
      ],
      "voiceNames": "Tenor Recorder",
      "detail": "LT F# → E (expected tonic G)"
    },
    {
      "rule": "Parallel P5ths",
      "measure": 11,
      "beat": 3,
      "timeDiv": 168,
      "partIndices": [
        0,
        2
      ],
      "voiceNames": "Soprano Recorder & Tenor Recorder",
      "detail": "P5 → P5 (A-D → G-C)",
      "noteTargets": [
        {
          "partIndex": 0,
          "startDiv": 164
        },
        {
          "partIndex": 2,
          "startDiv": 164
        },
        {
          "partIndex": 0,
          "startDiv": 168
        },
        {
          "partIndex": 2,
          "startDiv": 168
        }
      ]
    },
    {
      "rule": "Parallel octaves",
      "measure": 11,
      "beat": 4,
      "timeDiv": 172,
      "partIndices": [
        1,
        2
      ],
      "voiceNames": "Alto Recorder & Tenor Recorder",
      "detail": "P8 → P8 (C-C → D-D)",
      "noteTargets": [
        {
          "partIndex": 1,
          "startDiv": 168
        },
        {
          "partIndex": 2,
          "startDiv": 168
        },
        {
          "partIndex": 1,
          "startDiv": 172
        },
        {
          "partIndex": 2,
          "startDiv": 172
        }
      ]
    },
    {
      "rule": "Leading tone unresolved",
      "measure": 11,
      "beat": 4,
      "timeDiv": 172,
      "partIndices": [
        0
      ],
      "voiceNames": "Soprano Recorder",
      "detail": "LT F# → E (expected tonic G)"
    },
    {
      "rule": "Parallel P5ths",
      "measure": 12,
      "beat": 2,
      "timeDiv": 180,
      "partIndices": [
        0,
        3
      ],
      "voiceNames": "Soprano Recorder & Bass Recorder",
      "detail": "P5 → P5 (E-A → D-G)",
      "noteTargets": [
        {
          "partIndex": 0,
          "startDiv": 176
        },
        {
          "partIndex": 3,
          "startDiv": 178
        },
        {
          "partIndex": 0,
          "startDiv": 180
        },
        {
          "partIndex": 3,
          "startDiv": 180
        }
      ]
    },
    {
      "rule": "Voice crossing",
      "measure": 12,
      "beat": 2.5,
      "timeDiv": 182,
      "partIndices": [
        2,
        3
      ],
      "voiceNames": "Tenor Recorder & Bass Recorder",
      "detail": "Tenor Recorder crosses Bass Recorder (A vs F#)"
    },
    {
      "rule": "Parallel octaves",
      "measure": 13,
      "beat": 1.5,
      "timeDiv": 194,
      "partIndices": [
        0,
        2
      ],
      "voiceNames": "Soprano Recorder & Tenor Recorder",
      "detail": "P8 → P8 (C#-C# → D-D)",
      "noteTargets": [
        {
          "partIndex": 0,
          "startDiv": 192
        },
        {
          "partIndex": 2,
          "startDiv": 192
        },
        {
          "partIndex": 0,
          "startDiv": 194
        },
        {
          "partIndex": 2,
          "startDiv": 194
        }
      ]
    },
    {
      "rule": "Parallel octaves",
      "measure": 13,
      "beat": 2,
      "timeDiv": 196,
      "partIndices": [
        0,
        2
      ],
      "voiceNames": "Soprano Recorder & Tenor Recorder",
      "detail": "P8 → P8 (D-D → E-E)",
      "noteTargets": [
        {
          "partIndex": 0,
          "startDiv": 194
        },
        {
          "partIndex": 2,
          "startDiv": 194
        },
        {
          "partIndex": 0,
          "startDiv": 196
        },
        {
          "partIndex": 2,
          "startDiv": 196
        }
      ]
    },
    {
      "rule": "Voice crossing",
      "measure": 13,
      "beat": 3,
      "timeDiv": 200,
      "partIndices": [
        1,
        3
      ],
      "voiceNames": "Alto Recorder & Bass Recorder",
      "detail": "Alto Recorder crosses Bass Recorder (G vs A)"
    },
    {
      "rule": "Leading tone unresolved",
      "measure": 13,
      "beat": 3.5,
      "timeDiv": 202,
      "partIndices": [
        2
      ],
      "voiceNames": "Tenor Recorder",
      "detail": "LT F# → A (expected tonic G)"
    },
    {
      "rule": "Large leap",
      "measure": 13,
      "beat": 4.5,
      "timeDiv": 206,
      "partIndices": [
        2
      ],
      "voiceNames": "Tenor Recorder",
      "detail": "leap of 12 semitones: A → A"
    },
    {
      "rule": "Large leap",
      "measure": 15,
      "beat": 2,
      "timeDiv": 228,
      "partIndices": [
        3
      ],
      "voiceNames": "Bass Recorder",
      "detail": "leap of 10 semitones: E → D"
    },
    {
      "rule": "Voice crossing",
      "measure": 15,
      "beat": 2.5,
      "timeDiv": 230,
      "partIndices": [
        1,
        2
      ],
      "voiceNames": "Alto Recorder & Tenor Recorder",
      "detail": "Alto Recorder crosses Tenor Recorder (F# vs G)"
    },
    {
      "rule": "Leading tone unresolved",
      "measure": 15,
      "beat": 2.5,
      "timeDiv": 230,
      "partIndices": [
        1
      ],
      "voiceNames": "Alto Recorder",
      "detail": "LT F# → E (expected tonic G)"
    },
    {
      "rule": "Leading tone unresolved",
      "measure": 15,
      "beat": 3,
      "timeDiv": 232,
      "partIndices": [
        0
      ],
      "voiceNames": "Soprano Recorder",
      "detail": "LT F# → E (expected tonic G)"
    },
    {
      "rule": "Parallel P5ths",
      "measure": 16,
      "beat": 1,
      "timeDiv": 240,
      "partIndices": [
        0,
        1
      ],
      "voiceNames": "Soprano Recorder & Alto Recorder",
      "detail": "P5 → P5 (F#-B → E-A)",
      "noteTargets": [
        {
          "partIndex": 0,
          "startDiv": 232
        },
        {
          "partIndex": 1,
          "startDiv": 238
        },
        {
          "partIndex": 0,
          "startDiv": 240
        },
        {
          "partIndex": 1,
          "startDiv": 240
        }
      ]
    },
    {
      "rule": "Voice crossing",
      "measure": 16,
      "beat": 1,
      "timeDiv": 240,
      "partIndices": [
        2,
        3
      ],
      "voiceNames": "Tenor Recorder & Bass Recorder",
      "detail": "Tenor Recorder crosses Bass Recorder (A vs C#)"
    },
    {
      "rule": "Large leap",
      "measure": 16,
      "beat": 1,
      "timeDiv": 240,
      "partIndices": [
        2
      ],
      "voiceNames": "Tenor Recorder",
      "detail": "leap of 12 semitones: A → A"
    },
    {
      "rule": "Voice crossing",
      "measure": 16,
      "beat": 1.5,
      "timeDiv": 242,
      "partIndices": [
        1,
        3
      ],
      "voiceNames": "Alto Recorder & Bass Recorder",
      "detail": "Alto Recorder crosses Bass Recorder (A vs G)"
    },
    {
      "rule": "Voice crossing",
      "measure": 16,
      "beat": 1.5,
      "timeDiv": 242,
      "partIndices": [
        2,
        3
      ],
      "voiceNames": "Tenor Recorder & Bass Recorder",
      "detail": "Tenor Recorder crosses Bass Recorder (B vs G)"
    },
    {
      "rule": "Melodic tritone",
      "measure": 16,
      "beat": 1.5,
      "timeDiv": 242,
      "partIndices": [
        3
      ],
      "voiceNames": "Bass Recorder",
      "detail": "tritone leap: C# → G"
    },
    {
      "rule": "Voice crossing",
      "measure": 16,
      "beat": 2,
      "timeDiv": 244,
      "partIndices": [
        1,
        2
      ],
      "voiceNames": "Alto Recorder & Tenor Recorder",
      "detail": "Alto Recorder crosses Tenor Recorder (E vs C#)"
    },
    {
      "rule": "Parallel octaves",
      "measure": 16,
      "beat": 3,
      "timeDiv": 248,
      "partIndices": [
        0,
        1
      ],
      "voiceNames": "Soprano Recorder & Alto Recorder",
      "detail": "P8 → P8 (E-E → D-D)",
      "noteTargets": [
        {
          "partIndex": 0,
          "startDiv": 240
        },
        {
          "partIndex": 1,
          "startDiv": 244
        },
        {
          "partIndex": 0,
          "startDiv": 248
        },
        {
          "partIndex": 1,
          "startDiv": 248
        }
      ]
    },
    {
      "rule": "Voice crossing",
      "measure": 16,
      "beat": 4,
      "timeDiv": 252,
      "partIndices": [
        1,
        3
      ],
      "voiceNames": "Alto Recorder & Bass Recorder",
      "detail": "Alto Recorder crosses Bass Recorder (C# vs E)"
    },
    {
      "rule": "Leading tone unresolved",
      "measure": 17,
      "beat": 2.5,
      "timeDiv": 262,
      "partIndices": [
        2
      ],
      "voiceNames": "Tenor Recorder",
      "detail": "LT F# → E (expected tonic G)"
    },
    {
      "rule": "Voice crossing",
      "measure": 18,
      "beat": 1,
      "timeDiv": 272,
      "partIndices": [
        1,
        2
      ],
      "voiceNames": "Alto Recorder & Tenor Recorder",
      "detail": "Alto Recorder crosses Tenor Recorder (B vs A)"
    },
    {
      "rule": "Voice crossing",
      "measure": 18,
      "beat": 1,
      "timeDiv": 272,
      "partIndices": [
        2,
        3
      ],
      "voiceNames": "Tenor Recorder & Bass Recorder",
      "detail": "Tenor Recorder crosses Bass Recorder (A vs C#)"
    },
    {
      "rule": "Leading tone unresolved",
      "measure": 18,
      "beat": 3,
      "timeDiv": 280,
      "partIndices": [
        1
      ],
      "voiceNames": "Alto Recorder",
      "detail": "LT F# → B (expected tonic G)"
    },
    {
      "rule": "Parallel octaves",
      "measure": 19,
      "beat": 1,
      "timeDiv": 288,
      "partIndices": [
        0,
        3
      ],
      "voiceNames": "Soprano Recorder & Bass Recorder",
      "detail": "P8 → P8 (C#-C# → D-D)",
      "noteTargets": [
        {
          "partIndex": 0,
          "startDiv": 284
        },
        {
          "partIndex": 3,
          "startDiv": 286
        },
        {
          "partIndex": 0,
          "startDiv": 288
        },
        {
          "partIndex": 3,
          "startDiv": 288
        }
      ]
    },
    {
      "rule": "Parallel P5ths",
      "measure": 19,
      "beat": 3,
      "timeDiv": 296,
      "partIndices": [
        0,
        3
      ],
      "voiceNames": "Soprano Recorder & Bass Recorder",
      "detail": "P5 → P5 (E-A → D-G)",
      "noteTargets": [
        {
          "partIndex": 0,
          "startDiv": 292
        },
        {
          "partIndex": 3,
          "startDiv": 294
        },
        {
          "partIndex": 0,
          "startDiv": 296
        },
        {
          "partIndex": 3,
          "startDiv": 296
        }
      ]
    },
    {
      "rule": "Voice crossing",
      "measure": 21,
      "beat": 1,
      "timeDiv": 320,
      "partIndices": [
        0,
        1
      ],
      "voiceNames": "Soprano Recorder & Alto Recorder",
      "detail": "Soprano Recorder crosses Alto Recorder (D vs A)"
    },
    {
      "rule": "Parallel octaves",
      "measure": 21,
      "beat": 1,
      "timeDiv": 320,
      "partIndices": [
        1,
        3
      ],
      "voiceNames": "Alto Recorder & Bass Recorder",
      "detail": "P8 → P8 (G-G → A-A)",
      "noteTargets": [
        {
          "partIndex": 1,
          "startDiv": 318
        },
        {
          "partIndex": 3,
          "startDiv": 316
        },
        {
          "partIndex": 1,
          "startDiv": 320
        },
        {
          "partIndex": 3,
          "startDiv": 320
        }
      ]
    },
    {
      "rule": "Parallel P5ths",
      "measure": 21,
      "beat": 2,
      "timeDiv": 324,
      "partIndices": [
        0,
        3
      ],
      "voiceNames": "Soprano Recorder & Bass Recorder",
      "detail": "P5 → P5 (E-A → F#-B)",
      "noteTargets": [
        {
          "partIndex": 0,
          "startDiv": 322
        },
        {
          "partIndex": 3,
          "startDiv": 320
        },
        {
          "partIndex": 0,
          "startDiv": 324
        },
        {
          "partIndex": 3,
          "startDiv": 324
        }
      ]
    },
    {
      "rule": "Leading tone unresolved",
      "measure": 21,
      "beat": 2,
      "timeDiv": 324,
      "partIndices": [
        0
      ],
      "voiceNames": "Soprano Recorder",
      "detail": "LT F# → D (expected tonic G)"
    },
    {
      "rule": "Leading tone unresolved",
      "measure": 21,
      "beat": 2,
      "timeDiv": 324,
      "partIndices": [
        1
      ],
      "voiceNames": "Alto Recorder",
      "detail": "LT F# → C# (expected tonic G)"
    },
    {
      "rule": "Voice crossing",
      "measure": 22,
      "beat": 2,
      "timeDiv": 340,
      "partIndices": [
        1,
        2
      ],
      "voiceNames": "Alto Recorder & Tenor Recorder",
      "detail": "Alto Recorder crosses Tenor Recorder (C# vs A)"
    },
    {
      "rule": "Leading tone unresolved",
      "measure": 23,
      "beat": 1,
      "timeDiv": 352,
      "partIndices": [
        0
      ],
      "voiceNames": "Soprano Recorder",
      "detail": "LT F# → D (expected tonic G)"
    },
    {
      "rule": "Voice crossing",
      "measure": 23,
      "beat": 2,
      "timeDiv": 356,
      "partIndices": [
        1,
        2
      ],
      "voiceNames": "Alto Recorder & Tenor Recorder",
      "detail": "Alto Recorder crosses Tenor Recorder (D vs E)"
    },
    {
      "rule": "Parallel P5ths",
      "measure": 24,
      "beat": 4,
      "timeDiv": 380,
      "partIndices": [
        2,
        3
      ],
      "voiceNames": "Tenor Recorder & Bass Recorder",
      "detail": "P5 → P5 (C#-F# → D-G)",
      "noteTargets": [
        {
          "partIndex": 2,
          "startDiv": 378
        },
        {
          "partIndex": 3,
          "startDiv": 376
        },
        {
          "partIndex": 2,
          "startDiv": 380
        },
        {
          "partIndex": 3,
          "startDiv": 380
        }
      ]
    },
    {
      "rule": "Parallel unisons",
      "measure": 25,
      "beat": 1,
      "timeDiv": 384,
      "partIndices": [
        1,
        3
      ],
      "voiceNames": "Alto Recorder & Bass Recorder",
      "detail": "unison → unison on A",
      "noteTargets": [
        {
          "partIndex": 1,
          "startDiv": 382
        },
        {
          "partIndex": 3,
          "startDiv": 380
        },
        {
          "partIndex": 1,
          "startDiv": 384
        },
        {
          "partIndex": 3,
          "startDiv": 384
        }
      ]
    },
    {
      "rule": "Voice crossing",
      "measure": 27,
      "beat": 3,
      "timeDiv": 424,
      "partIndices": [
        1,
        2
      ],
      "voiceNames": "Alto Recorder & Tenor Recorder",
      "detail": "Alto Recorder crosses Tenor Recorder (F# vs D)"
    },
    {
      "rule": "Leading tone unresolved",
      "measure": 28,
      "beat": 1,
      "timeDiv": 432,
      "partIndices": [
        1
      ],
      "voiceNames": "Alto Recorder",
      "detail": "LT F# → E (expected tonic G)"
    },
    {
      "rule": "Parallel octaves",
      "measure": 29,
      "beat": 1,
      "timeDiv": 448,
      "partIndices": [
        1,
        3
      ],
      "voiceNames": "Alto Recorder & Bass Recorder",
      "detail": "P8 → P8 (G-G → A-A)",
      "noteTargets": [
        {
          "partIndex": 1,
          "startDiv": 446
        },
        {
          "partIndex": 3,
          "startDiv": 444
        },
        {
          "partIndex": 1,
          "startDiv": 448
        },
        {
          "partIndex": 3,
          "startDiv": 448
        }
      ]
    },
    {
      "rule": "Voice crossing",
      "measure": 29,
      "beat": 4,
      "timeDiv": 460,
      "partIndices": [
        2,
        3
      ],
      "voiceNames": "Tenor Recorder & Bass Recorder",
      "detail": "Tenor Recorder crosses Bass Recorder (A vs D)"
    },
    {
      "rule": "Large leap",
      "measure": 29,
      "beat": 4,
      "timeDiv": 460,
      "partIndices": [
        3
      ],
      "voiceNames": "Bass Recorder",
      "detail": "leap of 12 semitones: D → D"
    },
    {
      "rule": "Voice crossing",
      "measure": 30,
      "beat": 1,
      "timeDiv": 464,
      "partIndices": [
        2,
        3
      ],
      "voiceNames": "Tenor Recorder & Bass Recorder",
      "detail": "Tenor Recorder crosses Bass Recorder (D vs G)"
    },
    {
      "rule": "Large leap",
      "measure": 30,
      "beat": 1,
      "timeDiv": 464,
      "partIndices": [
        1
      ],
      "voiceNames": "Alto Recorder",
      "detail": "leap of 14 semitones: A → G"
    },
    {
      "rule": "Voice crossing",
      "measure": 30,
      "beat": 2,
      "timeDiv": 468,
      "partIndices": [
        1,
        3
      ],
      "voiceNames": "Alto Recorder & Bass Recorder",
      "detail": "Alto Recorder crosses Bass Recorder (D vs B)"
    },
    {
      "rule": "Large leap",
      "measure": 31,
      "beat": 1,
      "timeDiv": 480,
      "partIndices": [
        0
      ],
      "voiceNames": "Soprano Recorder",
      "detail": "leap of 11 semitones: C# → D"
    },
    {
      "rule": "Parallel octaves",
      "measure": 31,
      "beat": 2,
      "timeDiv": 484,
      "partIndices": [
        0,
        1
      ],
      "voiceNames": "Soprano Recorder & Alto Recorder",
      "detail": "P8 → P8 (A-A → G-G)",
      "noteTargets": [
        {
          "partIndex": 0,
          "startDiv": 482
        },
        {
          "partIndex": 1,
          "startDiv": 480
        },
        {
          "partIndex": 0,
          "startDiv": 484
        },
        {
          "partIndex": 1,
          "startDiv": 484
        }
      ]
    },
    {
      "rule": "Leading tone unresolved",
      "measure": 31,
      "beat": 2.5,
      "timeDiv": 486,
      "partIndices": [
        0
      ],
      "voiceNames": "Soprano Recorder",
      "detail": "LT F# → E (expected tonic G)"
    },
    {
      "rule": "Leading tone unresolved",
      "measure": 31,
      "beat": 3,
      "timeDiv": 488,
      "partIndices": [
        2
      ],
      "voiceNames": "Tenor Recorder",
      "detail": "LT F# → E (expected tonic G)"
    },
    {
      "rule": "Voice crossing",
      "measure": 32,
      "beat": 1,
      "timeDiv": 496,
      "partIndices": [
        1,
        3
      ],
      "voiceNames": "Alto Recorder & Bass Recorder",
      "detail": "Alto Recorder crosses Bass Recorder (F# vs C)"
    },
    {
      "rule": "Voice crossing",
      "measure": 32,
      "beat": 1,
      "timeDiv": 496,
      "partIndices": [
        2,
        3
      ],
      "voiceNames": "Tenor Recorder & Bass Recorder",
      "detail": "Tenor Recorder crosses Bass Recorder (E vs C)"
    },
    {
      "rule": "Leading tone unresolved",
      "measure": 32,
      "beat": 1,
      "timeDiv": 496,
      "partIndices": [
        1
      ],
      "voiceNames": "Alto Recorder",
      "detail": "LT F# → A (expected tonic G)"
    },
    {
      "rule": "Large leap",
      "measure": 32,
      "beat": 1,
      "timeDiv": 496,
      "partIndices": [
        3
      ],
      "voiceNames": "Bass Recorder",
      "detail": "leap of 14 semitones: D → C"
    },
    {
      "rule": "Parallel P5ths",
      "measure": 32,
      "beat": 2,
      "timeDiv": 500,
      "partIndices": [
        1,
        3
      ],
      "voiceNames": "Alto Recorder & Bass Recorder",
      "detail": "P5 → P5 (A-D → B-E)",
      "noteTargets": [
        {
          "partIndex": 1,
          "startDiv": 498
        },
        {
          "partIndex": 3,
          "startDiv": 498
        },
        {
          "partIndex": 1,
          "startDiv": 500
        },
        {
          "partIndex": 3,
          "startDiv": 500
        }
      ]
    },
    {
      "rule": "Voice crossing",
      "measure": 35,
      "beat": 1,
      "timeDiv": 544,
      "partIndices": [
        2,
        3
      ],
      "voiceNames": "Tenor Recorder & Bass Recorder",
      "detail": "Tenor Recorder crosses Bass Recorder (G vs E)"
    },
    {
      "rule": "Voice crossing",
      "measure": 36,
      "beat": 1,
      "timeDiv": 560,
      "partIndices": [
        2,
        3
      ],
      "voiceNames": "Tenor Recorder & Bass Recorder",
      "detail": "Tenor Recorder crosses Bass Recorder (F# vs A)"
    },
    {
      "rule": "Voice crossing",
      "measure": 37,
      "beat": 1,
      "timeDiv": 576,
      "partIndices": [
        2,
        3
      ],
      "voiceNames": "Tenor Recorder & Bass Recorder",
      "detail": "Tenor Recorder crosses Bass Recorder (F# vs D)"
    },
    {
      "rule": "Leading tone unresolved",
      "measure": 37,
      "beat": 1,
      "timeDiv": 576,
      "partIndices": [
        2
      ],
      "voiceNames": "Tenor Recorder",
      "detail": "LT F# → E (expected tonic G)"
    },
    {
      "rule": "Leading tone unresolved",
      "measure": 37,
      "beat": 2,
      "timeDiv": 580,
      "partIndices": [
        1
      ],
      "voiceNames": "Alto Recorder",
      "detail": "LT F# → E (expected tonic G)"
    },
    {
      "rule": "Voice crossing",
      "measure": 38,
      "beat": 1,
      "timeDiv": 592,
      "partIndices": [
        1,
        2
      ],
      "voiceNames": "Alto Recorder & Tenor Recorder",
      "detail": "Alto Recorder crosses Tenor Recorder (B vs D)"
    }
  ]
}